siwa/__init__.py
siwa/library/__init__.py
siwa/library/command_line.py
siwa/library/data.py
siwa/library/key_cache.py
siwa/library/key_protocol.py
siwa/library/public_key.py
siwa/library/token/__init__.py
siwa/library/token/header.py
siwa/library/token/payload.py
siwa/library/token/real_person.py
siwa/library/token/token.py
siwa/tests/__init__.py
siwa/tests/test.py
siwa/tests/test_result.py
siwa/tests/test_suite.py
siwa/tests/cases/__init__.py
siwa/tests/cases/parse_token.py
siwa/tests/cases/retrieve_public_key.py
siwa/tests/cases/verify_token_signature.py
siwa-0.0.7.dist-info/METADATA
siwa-0.0.7.dist-info/WHEEL
siwa-0.0.7.dist-info/top_level.txt
siwa-0.0.7.dist-info/RECORD
