Metadata-Version: 2.1
Name: siwa
Version: 0.0.7
Summary: Sign in with Apple
Home-page: https://github.com/procuret/procuret-python
Author: Hugh Jeremy
Author-email: hugh@blinkybeach.com
License: UNKNOWN
Project-URL: Github Repository, https://github.com/hwjeremy/siwa-python
Project-URL: About, https://github.com/hwjeremy/siwa-python
Keywords: library apple siwa signin
Platform: UNKNOWN
Classifier: Development Status :: 4 - Beta
Classifier: Intended Audience :: Developers
Classifier: License :: OSI Approved :: MIT License
Classifier: Natural Language :: English
Classifier: Programming Language :: Python :: 3 :: Only
Classifier: Programming Language :: Python :: 3.6
Classifier: Programming Language :: Python :: 3.7
Classifier: Programming Language :: Python :: 3.8
Classifier: Operating System :: OS Independent
Classifier: Topic :: Software Development :: Libraries
Requires-Python: >=3.6
Requires-Dist: PyJWT (>=2.2.0)
Requires-Dist: rsa
Requires-Dist: cryptography
